README.md
setup.cfg
setup.py
norm_evolution/__init__.py
norm_evolution/simulation.py
norm_evolution.egg-info/PKG-INFO
norm_evolution.egg-info/SOURCES.txt
norm_evolution.egg-info/dependency_links.txt
norm_evolution.egg-info/requires.txt
norm_evolution.egg-info/top_level.txt